{
  "mySLSettings": [
    {
      "myPort": "443",
      "myOutputFormat": "SVG",
      "myBaseURL": "service.semalogic.ddns.net",
      "myGetAPI": "/APIVersion",
      "mySID": "12345998",
      "myContext": true,
      "myUseHttp": false,
      "myUser": "User",
      "myPassword": "Password",
      "myUpdateInterval": 500,
      "myUseHttps": true,
      "myAspUrl": "",
      "myAspEndpoint": "",
      "myUseHttpsSL": true,
      "myUserSL": "User",
      "myPasswordSL": "Password"
    },
    {
      "myPort": "443",
      "myOutputFormat": "SVG",
      "myBaseURL": "semalogic-stage.cavas.uni-potsdam.de",
      "myGetAPI": "/APIVersion",
      "mySID": "12345655",
      "myContext": true,
      "myUseHttp": true,
      "myUser": "cavas",
      "myPassword": "cavasplus",
      "myUpdateInterval": 5000,
      "myUseHttps": true,
      "myAspUrl": "studyregulation-stage.cavas.uni-potsdam.de",
      "myAspEndpoint": "plans/count",
      "myUseHttpsSL": true,
      "myUserSL": "cavas",
      "myPasswordSL": "cavasplus"
    },
    {
      "myPort": "28000",
      "myOutputFormat": "SVG",
      "myBaseURL": "localhost",
      "myGetAPI": "/APIVersion",
      "mySID": "12345680",
      "myContext": true,
      "myUseHttp": false,
      "myUser": "cavas",
      "myPassword": "cavasplus",
      "myUpdateInterval": 500,
      "myUseHttps": true,
      "myAspUrl": "studyregulation-stage.cavas.uni-potsdam.de",
      "myAspEndpoint": "plans/count ",
      "myUseHttpsSL": false
    }
  ],
  "mySetting": 2,
  "myDebugLevel": 2
}